aiogram_loguru/__init__.py
aiogram_loguru/aiogramsink.py
aiogram_loguru/py.typed
aiogram_loguru-0.1.3.dist-info/METADATA
aiogram_loguru-0.1.3.dist-info/WHEEL
aiogram_loguru-0.1.3.dist-info/licenses/LICENSE
aiogram_loguru-0.1.3.dist-info/RECORD
