Metadata-Version: 2.4
Name: aiogram-loguru
Version: 0.1.3
Summary: A small library that ships some boilerplate code needed for integrating aiogram with loguru.
Project-URL: Source Code, https://github.com/antos07/aiogram-loguru
Author-email: Anton Trosenko <trotsenko.ant07@gmail.com>
License-Expression: MIT
License-File: LICENSE
Keywords: aiogram,loguru
Classifier: Development Status :: 3 - Alpha
Classifier: Framework :: AsyncIO
Classifier: Intended Audience :: Developers
Classifier: License :: OSI Approved :: MIT License
Classifier: Programming Language :: Python :: 3.9
Classifier: Programming Language :: Python :: 3.10
Classifier: Programming Language :: Python :: 3.11
Classifier: Programming Language :: Python :: 3.12
Classifier: Programming Language :: Python :: 3.13
Classifier: Topic :: Software Development :: Libraries :: Python Modules
Classifier: Typing :: Typed
Requires-Python: >=3.9
Requires-Dist: aiogram<3.21.0,>=3.18.0
Requires-Dist: loguru<0.8.0,>=0.7.0
